veriloghex/__init__.py
veriloghex/_version.py
veriloghex/veriloghex.py
veriloghex-0.1.2.dist-info/LICENSE
veriloghex-0.1.2.dist-info/METADATA
veriloghex-0.1.2.dist-info/WHEEL
veriloghex-0.1.2.dist-info/top_level.txt
veriloghex-0.1.2.dist-info/RECORD
