Metadata-Version: 2.1
Name: veriloghex
Version: 0.1.2
Summary: Loading from and dumping to Verilog Hex files
Author: Shareef Jalloq
Author-email: shareef.jalloq@idexbiometrics.com
License: MIT
Project-URL: homepage, https://github.com/idex-biometrics/veriloghex
Keywords: hex,verilog,vmem,readmemh
Classifier: Programming Language :: Python :: 3
Classifier: License :: OSI Approved :: MIT License
Requires-Python: >=3.6
License-File: LICENSE
